base32j.py
base32j-0.0.1.dist-info/LICENSE
base32j-0.0.1.dist-info/METADATA
base32j-0.0.1.dist-info/WHEEL
base32j-0.0.1.dist-info/top_level.txt
base32j-0.0.1.dist-info/RECORD
